Workbook

Sheet 📖 À LIRE
B7: 🎯 Objectif du cadre d'optimisation EROOM
B8: Ce diagnostic évalue la maturité d'un service numérique afin d'identifier ses principaux leviers d'optimisation : algorithme, code, architecture, opérations, données, hébergement, etc.
B9: Chaque question porte sur un facteur influençant la performance, l'efficacité ou la maintenabilité.
B10: Le diagnostic n'est pas une note de performance : il aide à déterminer les priorités d'action. Il n'y a pas de « bonnes » ou de « mauvaises » notes, seulement des possibilités d'amélioration.
B12: 📊 Échelle de notation
B13: Pour chaque critère, attribuez une note de 1 à 5 en fonction du niveau actuel de maîtrise.
B14: 1 = non maîtrisé / inconnu
B15: 5 = maîtrisé et mesuré
B16: Chaque question contribue de manière égale au score global, qui est ensuite converti en pourcentage de potentiel d'optimisation (0 % à 100 %).
B17: Ce pourcentage reflète la marge d'amélioration restante pour le service.
B18: Un score individuel faible met en évidence une possibilité d'amélioration, tandis qu'un score élevé indique que de bonnes pratiques sont déjà en place.
B20: 🧮 Interprétation des scores
... B79: La licence autorise l'utilisation commerciale. Si vous remixez, adaptez ou développez le contenu, vous devez accorder une licence au contenu modifié selon des conditions identiques. »

Sheet 🏦 0-Diagnostic rapide
C2: 🏦 Diagnostic rapide | F2: Potentiel d'optimisation
C3: Identifiez les meilleures opportunités d'optimisation. | F3: =IF(I4 = 0, 0, H4 / I4) -> 0.109375
F4: Un score plus élevé reflète un potentiel d'optimisation plus important. | H4: =SUM(H9:H25) -> 1.75 | I4: =SUM(I9:I25) -> 16
B7: Cet onglet propose un outil de diagnostic rapide permettant d'évaluer les produits numériques dans l'ensemble du système d'information et d'identifier ceux qui présentent le plus grand potentiel d'optimisation.
B8: ID | C8: CRITÈRE | D8: ✏️ ÉVALUATION | E8: MÉTHODES D'ÉVALUATION | F8: NIVEAU D'IMPACT | H8: Score | I8: Weight
B9: 0.1 | C9: La disparition du service numérique aurait-elle un impact important ? | D9: 1 | E9: 1 - Impact nul ou négligeable 2 - Impact limité sur un petit groupe d'utilisateurs ou de processus 3 - Impact modéré, mais des solutions de contournement existent 4 - Impact significatif sur les activités principales 5 - Impact critique (opérations bloquées, risque majeur pour l'entreprise ou l'infrastructure informatique) | F9: Déterminant | H9: =IF(AND(ISNUMBER(D9), D9>=1, D9<=5), (1-((D9-1)/4))*I9, 0*I9) -> 1 | I9: 1
B10: 0.2 | C10: Y a-t-il des fonctionnalités redondantes ou des applications en double dans le système ? | D10: 3 | E10: 1 - Quelque chose de très similaire existe déjà ailleurs (même fonctionnalité ou même code). 2 - Une partie existe déjà ailleurs. 3 - Il existe de petites similitudes, mais rien de majeur. 4 - Presque aucune similitude avec d'autres produits ou codes. 5 - Totalement unique ; rien de similaire n'existe. | F10: Déterminant | H10: =IF(AND(ISNUMBER(D10), D10>=1, D10<=5), (1-((D10-1)/4))*I10, 0*I10) -> 0.5 | I10: 1
B11: 0.3 | C11: Les composants principaux sont-ils soumis à des contraintes de haute disponibilité ? | D11: 4 | E11: 1 - 7 jours sur 7, 24 heures sur 24 - 99,99 % - Couverture internationale 2 - 7 jours sur 7, 24 heures sur 24 - 99 % 3 - Certains SLA. 4 - 5 jours sur 7, 8 heures sur 24 - Pas de SLA - Pas de Plan de reprise d'activité (DRP) 5 - Pas de SLA/SLO | F11: Déterminant | H11: =IF(AND(ISNUMBER(D11), D11>=1, D11<=5), (1-((D11-1)/4))*I11, 0*I11) -> 0.25 | I11: 1
B12: 0.4 | C12: Dépendances : combien de liens techniques vers d'autres systèmes sont en place ? | E12: 1 - Le produit n'est connecté à aucun autre système 2 - Le produit est connecté à quelques autres systèmes 3 - Le produit est connecté à certains autres systèmes et la connexion est importante (valeur commerciale et/ou couplage technique) 4 - Le produit est connecté à de nombreux autres systèmes 5 - Le produit est connecté à la plupart des autres systèmes du SI (par exemple : authentification et autorisation) | F12: Déterminant | H12: =IF(AND(ISNUMBER(D12), D12>=1, D12<=5), (1-((D12-1)/4))*I12, 0*I12) -> 0 | I12: 1
B13: 0.5 | C13: Le code source du projet est-il entièrement ou partiellement accessible à l'équipe ? | E13: 1 - Le code source est entièrement disponible (open source ou entièrement accessible à l'organisation). 2 - Le code source est principalement disponible (code accessible en interne, mais pas au public). 3 - Le code source est partiellement disponible (certains composants ou modules sont accessibles). 4 - L'accès est limité à un très petit groupe ou au fournisseur uniquement. 5 - Non, le code source n'est pas disponible / Je ne sais pas. | F13: Déterminant | H13: =IF(AND(ISNUMBER(D13), D13>=1, D13<=5), (1-((D13-1)/4))*I13, 0*I13) -> 0 | I13: 1
B14: 0.6 | C14: Les compétences nécessaires pour mettre à jour le service sont-elles disponibles ? | E14: 1 - L'équipe maîtrise bien la conception fonctionnelle et technique du projet et peut travailler en toute confiance. 2 - L'équipe connaît la majeure partie du projet et peut y travailler avec prudence. 3 - La connaissance du projet est insuffisante. 4 - Certaines personnes ont une connaissance partielle du projet. 5 - Personne ne connaît le projet. | F14: Déterminant | H14: =IF(AND(ISNUMBER(D14), D14>=1, D14<=5), (1-((D14-1)/4))*I14, 0*I14) -> 0 | I14: 1
B15: 0.7 | C15: La complexité de l'architecture est-elle élevée ? | E15: 1 - Très complexe / Je ne sais pas 2 - Complexe 3 - Moyen 4 - Simple 5 - Très simple | F15: Déterminant | H15: =IF(AND(ISNUMBER(D15), D15>=1, D15<=5), (1-((D15-1)/4))*I15, 0*I15) -> 0 | I15: 1
B16: 0.8 | C16: L'infrastructure (nombre et taille des composants tels que les machines virtuelles et les conteneurs) est-elle très importante ? | E16: 1 - L'une des plus grandes infrastructures de l'organisation 2 - Plus grande que la plupart des services 3 - Comparable à la moyenne de l'organisation 4 - Plus petite que la plupart des services 5 - Très petite (par exemple, quelques machines virtuelles ou conteneurs) | F16: Déterminant | H16: =IF(AND(ISNUMBER(D16), D16>=1, D16<=5), (1-((D16-1)/4))*I16, 0*I16) -> 0 | I16: 1
B17: 0.9 | C17: Un volume important de données est-il stocké ? | E17: 1 - Le produit dispose de l'un des plus grands volumes de stockage de données dans le SI / Je ne sais pas. 2 - Le produit stocke un volume important de données dans le SI par rapport à la plupart des systèmes. 3 - Le produit stocke une quantité moyenne de données par rapport au reste du SI. 4 - Le produit stocke une quantité limitée de données. 5 - Le produit stocke très peu de données. | F17: Déterminant | H17: =IF(AND(ISNUMBER(D17), D17>=1, D17<=5), (1-((D17-1)/4))*I17, 0*I17) -> 0 | I17: 1
B18: 0.10 | C18: La complexité fonctionnelle est-elle élevée ? | E18: 1 - Très complexe / Je ne sais pas 2 - Complexe 3 - Moyen 4 - Simple 5 - Facile | F18: Déterminant | H18: =IF(AND(ISNUMBER(D18), D18>=1, D18<=5), (1-((D18-1)/4))*I18, 0*I18) -> 0 | I18: 1
B19: 0.11 | C19: « Les parcours utilisateurs sont-ils fluides, intuitifs et exempts de frictions UX/UI susceptibles d'être améliorées ? » | E19: 1 - L'UX/UI est très médiocre, les utilisateurs se plaignent et/ou il y a des éléments en attente pour le modifier / Je ne sais pas 2 - L'UX/UI présente des points de friction récurrents ou des problèmes d'utilisabilité 3 - L'UX/UI est fonctionnelle, mais certains aspects pourraient être améliorés 4 - L'UX/UI est claire et agréable à utiliser, seules des améliorations mineures ont été identifiées 5 - L'UX/UI est bien conçue, testée par les utilisateurs et offre une expérience fluide et cohérente | F19: Déterminant | H19: =IF(AND(ISNUMBER(D19), D19>=1, D19<=5), (1-((D19-1)/4))*I19, 0*I19) -> 0 | I19: 1
B20: 0.12 | C20: Le produit est-il compatible avec le matériel le plus ancien de la flotte cible et offre-t-il une expérience fluide sur celui-ci ? | E20: 1 - Incompatible ou inconnu 2 - Compatible mais avec une dégradation significative (irritant ou frustrant pour l'utilisateur) 3 - Compatible et utilisable mais pas confortable (ralentissement notable) 4 - Compatible et généralement fluide (ralentissements mineurs) 5 - Compatible et fluide (confortable et réactif même sur du matériel ancien) | F20: Déterminant | H20: =IF(AND(ISNUMBER(D20), D20>=1, D20<=5), (1-((D20-1)/4))*I20, 0*I20) -> 0 | I20: 1
B21: 0.13 | C21: Le backlog produit contient-il des problèmes de performance et des améliorations ? | E21: 1 - Dans le backlog et discussion récurrente 3 - Quelques améliorations sont possibles 5 - Aucun problème de performance identifié | F21: Déterminant | H21: =IF(AND(ISNUMBER(D21), D21>=1, D21<=5), (1-((D21-1)/4))*I21, 0*I21) -> 0 | I21: 1
B22: 0.14 | C22: Les principales fonctionnalités sont-elles optimisées et efficaces ? | E22: 1 - Pas assez optimisé / ne sais pas 2 - Certaines fonctionnalités principales sont inefficaces ou redondantes 3 - Les fonctionnalités principales sont fonctionnelles mais pourraient être optimisées 4 - La plupart des fonctionnalités principales sont bien implémentées et fonctionnent efficacement 5 - Toutes les fonctionnalités principales sont pleinement efficaces, rationalisées et régulièrement revues à des fins d'optimisation | F22: Déterminant | H22: =IF(AND(ISNUMBER(D22), D22>=1, D22<=5), (1-((D22-1)/4))*I22, 0*I22) -> 0 | I22: 1
B23: 0.15 | C23: Existe-t-il une politique relative à la suppression et à l'archivage des données ? | E23: 1 - Aucune politique / ne sais pas 2 - Pratiques informelles ou ponctuelles de suppression et d'archivage 3 - Une politique existe, mais n'est pas appliquée de manière cohérente 4 - Une politique claire est en place et partiellement automatisée 5 - Une politique stricte, appliquée et régulièrement contrôlée en matière de suppression et d'archivage des données | F23: Déterminant | H23: =IF(AND(ISNUMBER(D23), D23>=1, D23<=5), (1-((D23-1)/4))*I23, 0*I23) -> 0 | I23: 1
B24: 0.16 | C24: Le service est-il hébergé dans un pays dont le mix électrique a un impact significatif ? (en fonction de l'emplacement) | E24: 1 - > 750 gCO2e / kWh 2- < 500 gCO2e / kWh 3- < 300 gCO2e / kWh 4- < 200 gCO2e / kWh 5- < 100 gCO2e / kWh | F24: Déterminant | H24: =IF(AND(ISNUMBER(D24), D24>=1, D24<=5), (1-((D24-1)/4))*I24, 0*I24) -> 0 | I24: 1
A26: Licence CC-BY-SA

Sheet 🛖 1-Produit
C2: 🛖 Produit | F2: Potentiel d'optimisation | I2: =SUM(I8:I24) -> 5 | J2: =SUM(J8:J24) -> 23.5 | K2: =SUM(K8:K24) -> 6.5
C3: Identifiez les meilleures opportunités d'optimisation. | F3: =IF(I2= 0, 0,K2 / J2) -> 0.27659574
F4: Un score plus élevé reflète un potentiel d'optimisation plus important. | I4: Score | J4: Weight | K4: Weighted Score
B7: ID | C7: CRITÈRE | D7: EXPLICATION SUPPLÉMENTAIRE | E7: ✏️ ÉVALUATION | F7: MÉTHODES D'ÉVALUATION | G7: NIVEAU D'IMPACT
B8: 1.1 | C8: Existe-t-il un moyen simple pour réaliser cette action ? | D8: S'il existe déjà un moyen de le faire, le moyen numérique apporte-t-il une valeur ajoutée à l'utilisateur ? | E8: ✅ Point fort confirmé | F8: Le critère est validé si : L'équipe a identifié une solution non numérique ou existante plus simple et démontré que la version numérique apporte clairement une valeur ajoutée par rapport à celle-ci (gain de temps, accessibilité, réduction de l'impact matériel). | G8: Déterminant | I8: =ifs( E8="🤔 À évaluer",0, E8="⌛️ Évaluation en cours",0.5, E8="✅ Point fort confirmé",0, E8="💡 Potentiel d'amélioration identifié",1, E8="🚫 Non applicable",0, TRUE, 0) -> 0 | J8: =ifs( G8="Modéré", 1, G8="Significatif", 1.5, G8="Déterminant", 2, TRUE,0) -> 2 | K8: =I8*J8 -> 0
B9: 1.2 | C9: Les utilisateurs cibles, avec leurs besoins professionnels, leurs appareils types et leurs attentes en matière d'ergonomie, sont-ils bien connus ? | D9: Le produit risque de ne pas être bien conçu si les utilisateurs cibles ne sont pas bien connus, ou mieux encore, impliqués dans le projet. Par exemple, les parcours utilisateurs pourraient être fastidieux ou la stratégie de compatibilité pourrait être inadéquate. | E9: 💡 Potentiel d'amélioration identifié | F9: Le critère est validé si : Les besoins et les contextes des utilisateurs sont documentés à l'aide de personas, d'entretiens, d'analyses d'utilisation, et les appareils courants sont bien connus et pris en compte dans la conception. | G9: Déterminant | I9: =ifs( E9="🤔 À évaluer",0, E9="⌛️ Évaluation en cours",0.5, E9="✅ Point fort confirmé",0, E9="💡 Potentiel d'amélioration identifié",1, E9="🚫 Non applicable",0, TRUE, 0) -> 1 | J9: =ifs( G9="Modéré", 1, G9="Significatif", 1.5, G9="Déterminant", 2, TRUE,0) -> 2 | K9: =I9*J9 -> 2
B10: 1.3 | C10: Les mises à jour des nouvelles fonctionnalités sont-elles obligatoires pour tous les appareils, quel que soit leur système d'exploitation ou leur navigateur ? | D10: Les nouvelles fonctionnalités alourdissent l'application. Sur les appareils plus anciens, les utilisateurs peuvent préférer conserver un produit plus simple, plus performant et moins gourmand en ressources. | E10: 🚫 Non applicable | F10: Le critère est validé si : Les tests montrent que la mise à jour ne dégrade pas les performances sur les appareils plus anciens ou modestes, et que le produit propose des modes optionnels ou allégés lorsque cela est nécessaire. | G10: Significatif | I10: =ifs( E10="🤔 À évaluer",0, E10="⌛️ Évaluation en cours",0.5, E10="✅ Point fort confirmé",0, E10="💡 Potentiel d'amélioration identifié",1, E10="🚫 Non applicable",0, TRUE, 0) -> 0 | J10: =ifs( G10="Modéré", 1, G10="Significatif", 1.5, G10="Déterminant", 2, TRUE,0) -> 1.5 | K10: =I10*J10 -> 0
B11: 1.4 | C11: La conception comprend-elle des composants personnalisés plutôt que des composants natifs ? | D11: Les composants système (boutons, menus, formulaires, etc.) sont presque toujours plus efficaces que ceux créés sur mesure. Sans parler de leur accessibilité et de leur compatibilité. | E11: 💡 Potentiel d'amélioration identifié | F11: Le critère est validé si : Les composants natifs sont préférés ou justifiés ; les composants personnalisés ne sont utilisés qu'en cas de nécessité et offrent des performances et une accessibilité équivalentes ou supérieures à celles des composants natifs. | G11: Modéré | I11: =ifs( E11="🤔 À évaluer",0, E11="⌛️ Évaluation en cours",0.5, E11="✅ Point fort confirmé",0, E11="💡 Potentiel d'amélioration identifié",1, E11="🚫 Non applicable",0, TRUE, 0) -> 1 | J11: =ifs( G11="Modéré", 1, G11="Significatif", 1.5, G11="Déterminant", 2, TRUE,0) -> 1 | K11: =I11*J11 -> 1
B12: 1.5 | C12: Y a-t-il des animations, des vidéos, des sons, des cartes (...) qui sont lus automatiquement ? | D12: La lecture de ce type de contenu sans aucune action de la part de l'utilisateur est gênante et utilise des ressources telles que la bande passante et le processeur graphique. | E12: 💡 Potentiel d'amélioration identifié | F12: Le critère est validé si : Aucun média n'est lancé sans action de l'utilisateur, ou la lecture automatique est techniquement nécessaire et optimisée (légère, désactivée par défaut, contrôlée par l'utilisateur). | G12: Modéré | I12: =ifs( E12="🤔 À évaluer",0, E12="⌛️ Évaluation en cours",0.5, E12="✅ Point fort confirmé",0, E12="💡 Potentiel d'amélioration identifié",1, E12="🚫 Non applicable",0, TRUE, 0) -> 1 | J12: =ifs( G12="Modéré", 1, G12="Significatif", 1.5, G12="Déterminant", 2, TRUE,0) -> 1 | K12: =I12*J12 -> 1
B13: 1.6 | C13: Est-il possible d'adapter les ressources utilisées par l'application à la configuration matérielle de l'utilisateur ? | D13: Tout le monde ne dispose pas d'un appareil capable d'exécuter des contenus gourmands en ressources informatiques (comme les contenus multimédias, etc.). Que se passe-t-il si un utilisateur tente d'exécuter un contenu gourmand en ressources informatiques sur un appareil inadapté ? Dans ce cas, idéalement, le service ne devrait pas bloquer l'accès et devrait exécuter les fonctions de base. | E13: 💡 Potentiel d'amélioration identifié | F13: Le critère est validé si : L'application détecte des conditions matérielles limitées et passe automatiquement à des comportements plus légers (qualité réduite, rendu simplifié, processus lourds désactivés). | G13: Modéré | I13: =ifs( E13="🤔 À évaluer",0, E13="⌛️ Évaluation en cours",0.5, E13="✅ Point fort confirmé",0, E13="💡 Potentiel d'amélioration identifié",1, E13="🚫 Non applicable",0, TRUE, 0) -> 1 | J13: =ifs( G13="Modéré", 1, G13="Significatif", 1.5, G13="Déterminant", 2, TRUE,0) -> 1 | K13: =I13*J13 -> 1
B14: 1.7 | C14: Toutes les fonctionnalités sont-elles utiles, utilisables et utilisées ? | D14: Simplifier le produit en supprimant les fonctionnalités inutilisées permettra de réduire la consommation de ressources. | F14: Le critère est validé si : Les données d'utilisation (analyses, journaux, commentaires) montrent que chaque fonctionnalité est réellement utilisée et apporte une valeur ajoutée évidente, et que les fonctionnalités inutilisées ou redondantes sont identifiées et supprimées afin de réduire la consommation de ressources. | G14: Significatif | I14: =ifs( E14="🤔 À évaluer",0, E14="⌛️ Évaluation en cours",0.5, E14="✅ Point fort confirmé",0, E14="💡 Potentiel d'amélioration identifié",1, E14="🚫 Non applicable",0, TRUE, 0) -> 0 | J14: =ifs( G14="Modéré", 1, G14="Significatif", 1.5, G14="Déterminant", 2, TRUE,0) -> 1.5 | K14: =I14*J14 -> 0
B15: 1.8 | C15: Le support des applications est-il médiocre sur les appareils les plus anciens ciblés ? | D15: La plupart des impacts des services numériques se font sentir du côté des appareils clients. Il est très important de ne pas pousser ces appareils à l'obsolescence en rompant leur compatibilité. | F15: Le critère est validé si : L'application fonctionne correctement sur les appareils les plus anciens du groupe cible, sans imposer de mises à niveau inutiles ni causer de problèmes de performances qui accélèrent l'obsolescence. | G15: Significatif | I15: =ifs( E15="🤔 À évaluer",0, E15="⌛️ Évaluation en cours",0.5, E15="✅ Point fort confirmé",0, E15="💡 Potentiel d'amélioration identifié",1, E15="🚫 Non applicable",0, TRUE, 0) -> 0 | J15: =ifs( G15="Modéré", 1, G15="Significatif", 1.5, G15="Déterminant", 2, TRUE,0) -> 1.5 | K15: =I15*J15 -> 0
B16: 1.9 | C16: Faut-il un réseau à haut débit pour utiliser l'application ? | D16: Une bande passante élevée implique une utilisation importante des ressources. Cela indique que certaines optimisations sont possibles pour réduire le nombre et/ou la taille des requêtes. | E16: 💡 Potentiel d'amélioration identifié | F16: Le critère est validé si : L'application reste utilisable sur des connexions à faible bande passante, grâce à des requêtes optimisées, des tailles de fichiers multimédias réduites, des stratégies de mise en cache ou un mode allégé. | G16: Significatif | I16: =ifs( E16="🤔 À évaluer",0, E16="⌛️ Évaluation en cours",0.5, E16="✅ Point fort confirmé",0, E16="💡 Potentiel d'amélioration identifié",1, E16="🚫 Non applicable",0, TRUE, 0) -> 1 | J16: =ifs( G16="Modéré", 1, G16="Significatif", 1.5, G16="Déterminant", 2, TRUE,0) -> 1.5 | K16: =I16*J16 -> 1.5
B17: 1.10 | C17: Le produit utilise-t-il des designs manupulateurs (UX dark patterns) qui augmentent l'utilisation des ressources ? | D17: Les mauvaises pratiques en matière d'expérience utilisateur comprennent le défilement infini, les abonnements pré-cochés, la difficulté à se désabonner, etc. | F17: Le critère est validé si : Aucun motif trompeur n'est présent et la conception évite les mécanismes tels que le défilement infini, la lecture automatique forcée ou les flux de désabonnement cachés qui augmentent artificiellement le chargement des pages et l'utilisation des données. | G17: Significatif | I17: =ifs( E17="🤔 À évaluer",0, E17="⌛️ Évaluation en cours",0.5, E17="✅ Point fort confirmé",0, E17="💡 Potentiel d'amélioration identifié",1, E17="🚫 Non applicable",0, TRUE, 0) -> 0 | J17: =ifs( G17="Modéré", 1, G17="Significatif", 1.5, G17="Déterminant", 2, TRUE,0) -> 1.5 | K17: =I17*J17 -> 0
B18: 1.11 | C18: Est-il possible de modifier les valeurs par défaut (nombre d'éléments affichés, qualité, fréquence de rafraîchissement, etc.) afin de réduire l'utilisation des ressources ? | D18: Les utilisateurs ne modifient généralement pas les valeurs par défaut. Définir des valeurs par défaut plus sobres peut permettre de réduire la consommation de ressources. | F18: Le critère est validé si : Les valeurs par défaut sont définies sur des options sobres et économes en ressources, et les utilisateurs peuvent facilement ajuster les paramètres (qualité, nombre d'affichages, fréquence) vers des modes plus exigeants uniquement si nécessaire. | G18: Significatif | I18: =ifs( E18="🤔 À évaluer",0, E18="⌛️ Évaluation en cours",0.5, E18="✅ Point fort confirmé",0, E18="💡 Potentiel d'amélioration identifié",1, E18="🚫 Non applicable",0, TRUE, 0) -> 0 | J18: =ifs( G18="Modéré", 1, G18="Significatif", 1.5, G18="Déterminant", 2, TRUE,0) -> 1.5 | K18: =I18*J18 -> 0
B19: 1.12 | C19: Y a-t-il beaucoup de pisteurs (trackers) sur le produit ? | D19: Les outils d'analyse et de suivi marketing sont souvent responsables de plus d'un tiers des requêtes sur les sites web. Limiter le nombre d'outils et de partenaires permettrait de réduire l'utilisation des ressources et d'améliorer la confidentialité. | F19: Le critère est validé si : Le suivi est strictement limité au strict nécessaire, le nombre de traceurs/outils est réduit au minimum et chaque demande de suivi est justifiée. La suppression des traceurs inutiles réduit la charge réseau et améliore la confidentialité. | G19: Significatif | I19: =ifs( E19="🤔 À évaluer",0, E19="⌛️ Évaluation en cours",0.5, E19="✅ Point fort confirmé",0, E19="💡 Potentiel d'amélioration identifié",1, E19="🚫 Non applicable",0, TRUE, 0) -> 0 | J19: =ifs( G19="Modéré", 1, G19="Significatif", 1.5, G19="Déterminant", 2, TRUE,0) -> 1.5 | K19: =I19*J19 -> 0
B20: 1.13 | C20: Les principaux parcours utilisateurs sont-ils optimisés pour être fluides et efficaces ? | D20: Des parcours utilisateur efficaces avec peu d'écrans réduisent l'utilisation des ressources et améliorent la satisfaction et la productivité des utilisateurs. | F20: Le critère est validé si : Les principaux flux de travail nécessitent un nombre minimal d'étapes/d'écrans, sans navigation redondante, ce qui améliore l'efficacité et réduit le nombre de requêtes serveur ou client. | G20: Significatif | I20: =ifs( E20="🤔 À évaluer",0, E20="⌛️ Évaluation en cours",0.5, E20="✅ Point fort confirmé",0, E20="💡 Potentiel d'amélioration identifié",1, E20="🚫 Non applicable",0, TRUE, 0) -> 0 | J20: =ifs( G20="Modéré", 1, G20="Significatif", 1.5, G20="Déterminant", 2, TRUE,0) -> 1.5 | K20: =I20*J20 -> 0
B21: 1.14 | C21: Les écrans principaux sont-ils clairs et bien conçus ? | D21: Les écrans les plus utilisés doivent être légers en termes d'informations affichées et de supports afin de réduire l'utilisation des ressources. | F21: Le critère est validé si : Les écrans les plus fréquemment utilisés ne contiennent que les informations nécessaires, utilisent des supports légers et évitent les scripts ou composants lourds qui augmentent le coût de rendu. | G21: Significatif | I21: =ifs( E21="🤔 À évaluer",0, E21="⌛️ Évaluation en cours",0.5, E21="✅ Point fort confirmé",0, E21="💡 Potentiel d'amélioration identifié",1, E21="🚫 Non applicable",0, TRUE, 0) -> 0 | J21: =ifs( G21="Modéré", 1, G21="Significatif", 1.5, G21="Déterminant", 2, TRUE,0) -> 1.5 | K21: =I21*J21 -> 0
B22: 1.15 | C22: Ce service est-il fréquemment utilisé ? | D22: Un service rarement utilisé mais fonctionnant en continu peut avoir un impact environnemental inutile. À l'inverse, un service fréquemment utilisé justifie sa consommation de ressources. Comprendre la fréquence d'utilisation permet d'évaluer si le service doit rester tel quel, être simplifié, être partiellement mis hors service ou passer à une exécution à la demande. | E22: ✅ Point fort confirmé | F22: Le critère est validé si le service présente une utilisation régulière et significative, en adéquation avec son empreinte en termes de ressources. | G22: Significatif | I22: =ifs( E22="🤔 À évaluer",0, E22="⌛️ Évaluation en cours",0.5, E22="✅ Point fort confirmé",0, E22="💡 Potentiel d'amélioration identifié",1, E22="🚫 Non applicable",0, TRUE, 0) -> 0 | J22: =ifs( G22="Modéré", 1, G22="Significatif", 1.5, G22="Déterminant", 2, TRUE,0) -> 1.5 | K22: =I22*J22 -> 0
B23: 1.16 | C23: Volume (nombre d'utilisateurs) | D23: Connaître le nombre d'utilisateurs actifs permet de contextualiser l'impact environnemental et de déterminer si l'ampleur du service correspond à son audience réelle. Une infrastructure importante desservant une population réduite peut indiquer un surdimensionnement, tandis qu'une utilisation élevée peut justifier pleinement les ressources allouées. | F23: Le critère est validé si le volume d'utilisateurs du produit justifie son utilisation des ressources et son architecture. | G23: Significatif | I23: =ifs( E23="🤔 À évaluer",0, E23="⌛️ Évaluation en cours",0.5, E23="✅ Point fort confirmé",0, E23="💡 Potentiel d'amélioration identifié",1, E23="🚫 Non applicable",0, TRUE, 0) -> 0 | J23: =ifs( G23="Modéré", 1, G23="Significatif", 1.5, G23="Déterminant", 2, TRUE,0) -> 1.5 | K23: =I23*J23 -> 0
A25: Licence CC-BY-SA

Sheet 🗺️ 2-Architecture
C2: 🗺️ Architecture | F2: Potentiel d'optimisation | I2: =SUM(I8:I13) -> 3 | J2: =SUM(J8:J13) -> 8 | K2: =SUM(K8:K13) -> 5
C3: Identifiez les meilleures opportunités d'optimisation. | F3: =IF(I2= 0, 0,K2 / J2) -> 0.625
F4: Un score plus élevé reflète un potentiel d'optimisation plus important. | I4: Score | J4: Weight | K4: Weighted Score
B7: ID | C7: CRITÈRE | D7: EXPLICATION SUPPLÉMENTAIRE | E7: ✏️ ÉVALUATION | F7: MÉTHODES D'ÉVALUATION | G7: NIVEAU D'IMPACT
B8: 2.1 | C8: Le produit utilise-t-il des technologies gourmandes ? | D8: Si le produit utilise des technologies lourdes telles que l'IA générative ou la blockchain, il peut être possible de le remplacer ou d'utiliser des implémentations plus efficaces. | F8: Le critère est validé si la pile technique du projet ne comprend pas d'éléments lourds (tels que LLM ou blockchain basée sur la preuve) pouvant être remplacés par des alternatives plus légères. | G8: Significatif | I8: =ifs( E8="🤔 À évaluer",0, E8="⌛️ Évaluation en cours",0.5, E8="✅ Point fort confirmé",0, E8="💡 Potentiel d'amélioration identifié",1, E8="🚫 Non applicable",0, TRUE, 0) -> 0 | J8: =ifs( G8="Modéré", 1, G8="Significatif", 1.5, G8="Déterminant", 2, TRUE,0) -> 1.5 | K8: =I8*J8 -> 0
B9: 2.2 | C9: Il n'y a pas de stratégie de compatibilité. | D9: Le service doit être compatible avec tous les appareils dont disposent les utilisateurs afin d'éviter que ces appareils ne deviennent obsolètes. | E9: 💡 Potentiel d'amélioration identifié | F9: Il existe un potentiel d'amélioration si le projet n'utilise pas d'outils d'élasticité et si la charge n'est pas constante. Le service n'est pas compatible avec tous les appareils ciblés ou la liste des appareils ciblés n'est pas connue. | G9: Déterminant | I9: =ifs( E9="🤔 À évaluer",0, E9="⌛️ Évaluation en cours",0.5, E9="✅ Point fort confirmé",0, E9="💡 Potentiel d'amélioration identifié",1, E9="🚫 Non applicable",0, TRUE, 0) -> 1 | J9: =ifs( G9="Modéré", 1, G9="Significatif", 1.5, G9="Déterminant", 2, TRUE,0) -> 2 | K9: =I9*J9 -> 2
B10: 2.3 | C10: Est-il possible d'optimiser la séparation et la communication entre les composants ? | D10: Les choix architecturaux peuvent permettre une stratégie de mise à l'échelle efficace qui réduit l'utilisation des ressources, mais peuvent également entraîner une certaine surcharge si la séparation et le couplage des composants ne sont pas bien optimisés. | E10: 💡 Potentiel d'amélioration identifié | F10: Il existe un potentiel d'amélioration si les composants dépendent trop les uns des autres ou si leur communication entraîne des ralentissements, des erreurs ou une complexité inutile. | G10: Significatif | I10: =ifs( E10="🤔 À évaluer",0, E10="⌛️ Évaluation en cours",0.5, E10="✅ Point fort confirmé",0, E10="💡 Potentiel d'amélioration identifié",1, E10="🚫 Non applicable",0, TRUE, 0) -> 1 | J10: =ifs( G10="Modéré", 1, G10="Significatif", 1.5, G10="Déterminant", 2, TRUE,0) -> 1.5 | K10: =I10*J10 -> 1.5
B11: 2.4 | C11: Le pic de charge peut-il être lissé sur une échelle de temps ? | D11: Le déplacement des tâches dans le temps à l'aide du traitement par lots ou de courtiers de messages permet de lisser la charge et d'alléger l'infrastructure, car la charge maximale est moins importante. | E11: 💡 Potentiel d'amélioration identifié | F11: Il existe un potentiel d'amélioration si le projet n'utilise pas d'outils d'élasticité et si la charge n'est pas constante. L'application présente des pics de charge et les tâches ne doivent pas être exécutées immédiatement (il ne s'agit pas, par exemple, d'afficher des pages). | G11: Significatif | I11: =ifs( E11="🤔 À évaluer",0, E11="⌛️ Évaluation en cours",0.5, E11="✅ Point fort confirmé",0, E11="💡 Potentiel d'amélioration identifié",1, E11="🚫 Non applicable",0, TRUE, 0) -> 1 | J11: =ifs( G11="Modéré", 1, G11="Significatif", 1.5, G11="Déterminant", 2, TRUE,0) -> 1.5 | K11: =I11*J11 -> 1.5
B12: 2.5 | C12: Y a-t-il des calculs ou des requêtes lourds dont les résultats peuvent être mis en cache ? | D12: Si, au sein du système, certains calculs et requêtes lourds renvoient plusieurs fois les mêmes résultats, il peut être possible de les mettre en cache. Cela permettra d'économiser des ressources et d'améliorer les performances. | F12: Il existe un potentiel d'amélioration si le projet n'utilise pas d'outils élastiques (mécanismes d’auto-scaling) et si la charge n'est pas constante. l'application effectue des calculs lourds, dont le résultat est utilisé plusieurs fois. | G12: Significatif | I12: =ifs( E12="🤔 À évaluer",0, E12="⌛️ Évaluation en cours",0.5, E12="✅ Point fort confirmé",0, E12="💡 Potentiel d'amélioration identifié",1, E12="🚫 Non applicable",0, TRUE, 0) -> 0 | J12: =ifs( G12="Modéré", 1, G12="Significatif", 1.5, G12="Déterminant", 2, TRUE,0) -> 1.5 | K12: =I12*J12 -> 0
A14: Licence CC-BY-SA

Sheet 🏢 3-Infrastructure
C2: 🏢 Infrastructure | F2: Potentiel d'optimisation | I2: =SUM(I8:I16) -> 3 | J2: =SUM(J8:J16) -> 12 | K2: =SUM(K8:K16) -> 3
C3: Identifiez les meilleures opportunités d'optimisation. | F3: =IF(I2= 0, 0,K2 / J2) -> 0.25
F4: Un score plus élevé reflète un potentiel d'optimisation plus important. | I4: Score | J4: Weight | K4: Weighted Score
B7: ID | C7: CRITÈRE | D7: EXPLICATION SUPPLÉMENTAIRE | E7: ✏️ ÉVALUATION | F7: MÉTHODES D'ÉVALUATION | G7: NIVEAU D'IMPACT
B8: 45660 | C8: La facture peut-elle être réduite ? | D8: Le déploiement d'une stratégie FinOps/GreenOps permettra au produit d'utiliser moins de ressources. Presque toutes les pratiques FinOps (localisation des composants sous-utilisés, utilisation d'instances spot, ajustement de la taille des composants, utilisation de services gérés, etc.) permettent de réduire l'utilisation des ressources et, par conséquent, l'impact environnemental. Une stratégie visant à réduire l'impact environnemental est appelée GreenOps. | F8: Le point fort est confirmée si une stratégie est en place, sinon il existe un potentiel d'amélioration. | G8: Significatif | I8: =ifs( E8="🤔 À évaluer",0, E8="⌛️ Évaluation en cours",0.5, E8="✅ Point fort confirmé",0, E8="💡 Potentiel d'amélioration identifié",1, E8="🚫 Non applicable",0, TRUE, 0) -> 0 | J8: =ifs( G8="Modéré", 1, G8="Significatif", 1.5, G8="Déterminant", 2, TRUE,0) -> 1.5 | K8: =I8*J8 -> 0
B9: 45691 | C9: Il n'existe aucun système de suivi de l'impact environnemental. | D9: Surveillance des émissions de carbone et de l'intensité carbone ? Connaissez-vous les indices PUE et WUE de votre centre de données ? Envisagez-vous de déménager vers des sites plus écologiques ? | E9: 💡 Potentiel d'amélioration identifié | F9: Le point fort est confirmée si un suivi satisfaisant est en place, sinon il existe un potentiel d'amélioration. | G9: Significatif | I9: =ifs( E9="🤔 À évaluer",0, E9="⌛️ Évaluation en cours",0.5, E9="✅ Point fort confirmé",0, E9="💡 Potentiel d'amélioration identifié",1, E9="🚫 Non applicable",0, TRUE, 0) -> 1 | J9: =ifs( G9="Modéré", 1, G9="Significatif", 1.5, G9="Déterminant", 2, TRUE,0) -> 1.5 | K9: =I9*J9 -> 1.5
B10: 45719 | C10: Le service est-il hébergé dans une région où le mix électrique a un impact important ? | D10: Le mix électrique local est très important : le choix de la bonne région a un effet considérable sur les impacts liés à l'utilisation du service. | F10: Il existe un potentiel d'amélioration si le service n'est pas hébergé en France (ou dans un autre pays dont le mix électrique a un faible impact). | G10: Significatif | I10: =ifs( E10="🤔 À évaluer",0, E10="⌛️ Évaluation en cours",0.5, E10="✅ Point fort confirmé",0, E10="💡 Potentiel d'amélioration identifié",1, E10="🚫 Non applicable",0, TRUE, 0) -> 0 | J10: =ifs( G10="Modéré", 1, G10="Significatif", 1.5, G10="Déterminant", 2, TRUE,0) -> 1.5 | K10: =I10*J10 -> 0
B11: 45780 | C11: L'infrastructure peut-elle être mutualisée ? | D11: L'utilisation d'un hébergement mutualisé (via VM, conteneurs, services gérés, *aaS) permet de réduire l'utilisation des ressources, car celles-ci sont partagées avec d'autres produits. | E11: 💡 Potentiel d'amélioration identifié | F11: Il existe un potentiel d'amélioration si l'infrastructure du projet n'est pas, ou pas entièrement, mutualisée. | G11: Significatif | I11: =ifs( E11="🤔 À évaluer",0, E11="⌛️ Évaluation en cours",0.5, E11="✅ Point fort confirmé",0, E11="💡 Potentiel d'amélioration identifié",1, E11="🚫 Non applicable",0, TRUE, 0) -> 1 | J11: =ifs( G11="Modéré", 1, G11="Significatif", 1.5, G11="Déterminant", 2, TRUE,0) -> 1.5 | K11: =I11*J11 -> 1.5
B12: 45811 | C12: Les composants de déploiement (VM, serveur, conteneurs) sont-ils surdimensionnés ? | D12: Utilisez des outils/méthodologies d'observabilité pour vérifier la charge des machines virtuelles/serveurs (CPU/RAM). Elle doit être d'au moins 70 %. | F12: Il existe un potentiel d'amélioration si certains composants ont une charge (CPU ou RAM) inférieure à 70 %. | G12: Significatif | I12: =ifs( E12="🤔 À évaluer",0, E12="⌛️ Évaluation en cours",0.5, E12="✅ Point fort confirmé",0, E12="💡 Potentiel d'amélioration identifié",1, E12="🚫 Non applicable",0, TRUE, 0) -> 0 | J12: =ifs( G12="Modéré", 1, G12="Significatif", 1.5, G12="Déterminant", 2, TRUE,0) -> 1.5 | K12: =I12*J12 -> 0
B13: 45841 | C13: Des outils et des stratégies d'élasticité/d’auto-scaling peuvent-ils être déployés pour réduire la taille de l'infrastructure ? | D13: Grâce à des outils tels que les tâches cron, les orchestrateurs, les conteneurs ou les fonctions en tant que service, il est possible d'ajuster le nombre de composants déployés. Ainsi, si la charge est faible, le nombre de composants est faible. | F13: Il existe un potentiel d'amélioration si le projet n'utilise pas d'outils d’auto-scalin contrôlés (c'est-à-dire pas en mode barre libre, mais avec une limite raisonnable) et si la charge n'est pas constante. | G13: Significatif | I13: =ifs( E13="🤔 À évaluer",0, E13="⌛️ Évaluation en cours",0.5, E13="✅ Point fort confirmé",0, E13="💡 Potentiel d'amélioration identifié",1, E13="🚫 Non applicable",0, TRUE, 0) -> 0 | J13: =ifs( G13="Modéré", 1, G13="Significatif", 1.5, G13="Déterminant", 2, TRUE,0) -> 1.5
B14: 45872 | C14: Tous les environnements sont-ils toujours activés ? | D14: Les environnements qui ne sont pas utilisés (par exemple ceux qui ne sont pas en production la nuit ou le week-end) peuvent être désactivés. | E14: 💡 Potentiel d'amélioration identifié | F14: Il existe un potentiel d'amélioration si le produit dispose d'environnements d'exécution qui ne sont pas utilisés pendant une période significative (comme la nuit ou le week-end). | G14: Significatif | I14: =ifs( E14="🤔 À évaluer",0, E14="⌛️ Évaluation en cours",0.5, E14="✅ Point fort confirmé",0, E14="💡 Potentiel d'amélioration identifié",1, E14="🚫 Non applicable",0, TRUE, 0) -> 1 | J14: =ifs( G14="Modéré", 1, G14="Significatif", 1.5, G14="Déterminant", 2, TRUE,0) -> 1.5
B15: 45903 | C15: Les environnements de test sont-ils aussi grands que ceux de production ? | D15: Il n'est généralement pas nécessaire d'avoir autant de composants (VM, conteneurs) dans les environnements de test, sauf pour les tests de charge. | F15: Il existe un potentiel d'amélioration si certains environnements de test sont aussi grands que ceux de production. | G15: Significatif | I15: =ifs( E15="🤔 À évaluer",0, E15="⌛️ Évaluation en cours",0.5, E15="✅ Point fort confirmé",0, E15="💡 Potentiel d'amélioration identifié",1, E15="🚫 Non applicable",0, TRUE, 0) -> 0 | J15: =ifs( G15="Modéré", 1, G15="Significatif", 1.5, G15="Déterminant", 2, TRUE,0) -> 1.5

Sheet 💾 4-Stockage et données
C2: 💾 Storage & Data | F2: Potentiel d'optimisation | I2: =SUM(I8:I14) -> 3 | J2: =SUM(J8:J14) -> 8 | K2: =SUM(K8:K14) -> 4.5
C3: Identifiez les meilleures opportunités d'optimisation. | F3: =IF(I2= 0, 0,K2 / J2) -> 0.5625
F4: Un score plus élevé reflète un potentiel d'optimisation plus important. | I4: Score | J4: Weight | K4: Weighted Score
B7: ID # | C7: CRITÈRE | D7: EXPLICATION SUPPLÉMENTAIRE | E7: ✏️ ÉVALUATION | F7: MÉTHODES D'ÉVALUATION | G7: NIVEAU D'IMPACT
B8: 45661 | C8: Des mécanismes de suppression et d'archivage sont-ils mis en place ? | D8: Sans suppression ou archivage automatisés, les données s'accumulent inutilement et augmentent l'utilisation de l'espace de stockage. Les règles de conservation et les politiques d'archivage limitent la croissance des données et réduisent l'impact environnemental. | E8: 💡 Potentiel d'amélioration identifié | F8: Le critère est validé si des mécanismes automatiques de suppression et d'archivage existent et sont effectivement appliqués. | G8: Significatif | I8: =ifs( E8="🤔 À évaluer",0, E8="⌛️ Évaluation en cours",0.5, E8="✅ Point fort confirmé",0, E8="💡 Potentiel d'amélioration identifié",1, E8="🚫 Non applicable",0, TRUE, 0) -> 1 | J8: =ifs( G8="Modéré", 1, G8="Significatif", 1.5, G8="Déterminant", 2, TRUE,0) -> 1.5 | K8: =I8*J8 -> 1.5
B9: 45692 | C9: Les meilleures pratiques en matière de bases de données sont-elles mises en place ? | D9: Une base de données non optimisée nécessite davantage de ressources CPU, de mémoire ou d'E/S pour fournir le même niveau de service, ce qui augmente la consommation d'énergie. Un indexage approprié, une bonne modélisation des données et une maintenance régulière contribuent à réduire l'utilisation inutile des ressources. | E9: 💡 Potentiel d'amélioration identifié | F9: Le critère est validé si une stratégie est appliquée pour optimiser les performances de la base de données. | G9: Significatif | I9: =ifs( E9="🤔 À évaluer",0, E9="⌛️ Évaluation en cours",0.5, E9="✅ Point fort confirmé",0, E9="💡 Potentiel d'amélioration identifié",1, E9="🚫 Non applicable",0, TRUE, 0) -> 1 | J9: =ifs( G9="Modéré", 1, G9="Significatif", 1.5, G9="Déterminant", 2, TRUE,0) -> 1.5 | K9: =I9*J9 -> 1.5
B10: 45720 | C10: Le produit utilise-t-il les technologies de base de données/stockage adaptées aux utilisations prévues ? | D10: Si les besoins en stockage de produits sont importants, il peut être avantageux de spécialiser les technologies de stockage : - PG/MYSQL/Oracle/SQLServer ou relationnel-objet - MongoDB pour les documents orientés. - Base de données en colonnes pour l'analyse. - Base de données spécialisée (vecteur, séries chronologiques). | E10: ✅ Point fort confirmé | F10: Il existe un potentiel d'amélioration si le projet n'utilise pas d'outils d'élasticité (d'auto-scalling) et si la charge n'est pas constante. Le projet présente des besoins de stockage spécifiques qui seraient mieux pris en charge par un autre système de stockage, et le volume est important (> plusieurs centaines de Go). | G10: Significatif | I10: =ifs( E10="🤔 À évaluer",0, E10="⌛️ Évaluation en cours",0.5, E10="✅ Point fort confirmé",0, E10="💡 Potentiel d'amélioration identifié",1, E10="🚫 Non applicable",0, TRUE, 0) -> 0 | J10: =ifs( G10="Modéré", 1, G10="Significatif", 1.5, G10="Déterminant", 2, TRUE,0) -> 1.5 | K10: =I10*J10 -> 0
B11: 45751 | C11: Les bases de données de test sont-elles aussi volumineuses que celles de production ? | D11: En général, il n'est pas nécessaire d'avoir autant de données dans les environnements de test qu'en production. | E11: 💡 Potentiel d'amélioration identifié | F11: Il existe un potentiel d'amélioration si certaines bases de données de test sont aussi volumineuses que celles de production. | G11: Significatif | I11: =ifs( E11="🤔 À évaluer",0, E11="⌛️ Évaluation en cours",0.5, E11="✅ Point fort confirmé",0, E11="💡 Potentiel d'amélioration identifié",1, E11="🚫 Non applicable",0, TRUE, 0) -> 1 | J11: =ifs( G11="Modéré", 1, G11="Significatif", 1.5, G11="Déterminant", 2, TRUE,0) -> 1.5 | K11: =I11*J11 -> 1.5
B12: 45781 | C12: Y a-t-il des doublons dans les données ? | D12: Si les données sont dupliquées et que cela ne fait pas partie de la stratégie produit en matière de haute disponibilité, cela indique généralement une opportunité d'optimisation, sauf lorsque la duplication résulte d'une dénormalisation intentionnelle motivée par des considérations de performance. | F12: Le critère est validé si l'équipe a identifié les données dupliquées et déterminé si cela est justifié ou non. | G12: Modéré | I12: =ifs( E12="🤔 À évaluer",0, E12="⌛️ Évaluation en cours",0.5, E12="✅ Point fort confirmé",0, E12="💡 Potentiel d'amélioration identifié",1, E12="🚫 Non applicable",0, TRUE, 0) -> 0 | J12: =ifs( G12="Modéré", 1, G12="Significatif", 1.5, G12="Déterminant", 2, TRUE,0) -> 1 | K12: =I12*J12 -> 0
B13: 45812 | C13: Existe-t-il des données qui sont très rarement utilisées dans le service et qui pourraient être transférées vers un stockage à froid ? | D13: Les données rarement consultées peuvent être transférées vers un niveau de stockage plus économe en énergie, mais plus lent (« stockage à froid »). Par exemple, les transactions datant de plus de trois mois dans un service bancaire peuvent être supprimées de la base de données principale et archivées. L'utilisateur peut toujours les récupérer, mais via un processus plus lent, ce qui est acceptable compte tenu de leur utilisation peu fréquente. Par exemple : les SSD ont un impact carbone 2 à 3 fois plus élevé que les disques durs mécaniques (HDD) de capacité équivalente | F13: Le critère est validé si les données rarement consultées ont déjà été transférées vers un stockage froid ou hiérarchisé approprié. | G13: Modéré | I13: =ifs( E13="🤔 À évaluer",0, E13="⌛️ Évaluation en cours",0.5, E13="✅ Point fort confirmé",0, E13="💡 Potentiel d'amélioration identifié",1, E13="🚫 Non applicable",0, TRUE, 0) -> 0 | J13: =ifs( G13="Modéré", 1, G13="Significatif", 1.5, G13="Déterminant", 2, TRUE,0) -> 1

Sheet 👨‍💻5-Algo & Code
C2: 👨‍💻 Algo & Code | F2: Potentiel d'optimisation | I2: =SUM(I8:I17) -> 3.5 | J2: =SUM(J8:J17) -> 13 | K2: =SUM(K8:K16) -> 4.75
C3: Identifiez les meilleures opportunités d'optimisation. | F3: =IF(I2= 0, 0,K2 / J2) -> 0.36538462
F4: Un score plus élevé reflète un potentiel d'optimisation plus important. | I4: Score | J4: Weight | K4: Weighted Score
B7: ID # | C7: CRITÈRE | D7: EXPLICATION SUPPLÉMENTAIRE | E7: ✏️ ÉVALUATION | F7: MÉTHODES D'ÉVALUATION | G7: NIVEAU D'IMPACT
B8: 45662 | C8: Existe-t-il des outils d'analyse statistique permettant de mettre en évidence des améliorations potentielles en matière d'efficacité ? | D8: L'analyse statique permet d'identifier les problèmes de performance et d'efficacité. Elle contribue également à améliorer la qualité et facilite la modification des produits. | E8: ✅ Point fort confirmé | F8: Une amélioration est identifiée si les outils d'analyse statistique en place ont révélé des gains d'efficacité potentiels. | G8: Modéré | I8: =ifs( E8="🤔 À évaluer",0, E8="⌛️ Évaluation en cours",0.5, E8="✅ Point fort confirmé",0, E8="💡 Potentiel d'amélioration identifié",1, E8="🚫 Non applicable",0, TRUE, 0) -> 0 | J8: =ifs( G8="Modéré", 1, G8="Significatif", 1.5, G8="Déterminant", 2, TRUE,0) -> 1 | K8: =I8*J8 -> 0
B9: 45693 | C9: Une campagne de tests de charge ou de résistance a-t-elle révélé des problèmes d'efficacité ? | D9: Si une campagne de tests de charge ou de résistance a révélé des problèmes d'efficacité, il peut être possible d'améliorer le produit. | E9: 💡 Potentiel d'amélioration identifié | F9: Une amélioration est identifiée si une campagne de tests de charge ou de résistance a révélé des problèmes d'efficacité. | G9: Significatif | I9: =ifs( E9="🤔 À évaluer",0, E9="⌛️ Évaluation en cours",0.5, E9="✅ Point fort confirmé",0, E9="💡 Potentiel d'amélioration identifié",1, E9="🚫 Non applicable",0, TRUE, 0) -> 1 | J9: =ifs( G9="Modéré", 1, G9="Significatif", 1.5, G9="Déterminant", 2, TRUE,0) -> 1.5 | K9: =I9*J9 -> 1.5
B10: 45721 | C10: L'équipe a-t-elle identifié des domaines à améliorer en termes de performance/efficacité et les a-t-elle ajoutés au backlog ? | D10: Une amélioration est identifiée si l'équipe a identifié des gains d'efficacité. | E10: 💡 Potentiel d'amélioration identifié | F10: Le critère est validé si les tâches identifiées par l'équipe (problèmes, tickets, etc.) comportent des points permettant d'améliorer les performances/l'efficacité. | G10: Significatif | I10: =ifs( E10="🤔 À évaluer",0, E10="⌛️ Évaluation en cours",0.5, E10="✅ Point fort confirmé",0, E10="💡 Potentiel d'amélioration identifié",1, E10="🚫 Non applicable",0, TRUE, 0) -> 1 | J10: =ifs( G10="Modéré", 1, G10="Significatif", 1.5, G10="Déterminant", 2, TRUE,0) -> 1.5 | K10: =I10*J10 -> 1.5
B11: 45752 | C11: Les indicateurs de performance sont-ils médiocres ? | D11: Une mauvaise performance implique un potentiel d'optimisation. Les indicateurs de performance comprennent la latence, les requêtes par seconde, les indicateurs Core Web Vitals, etc. | E11: 💡 Potentiel d'amélioration identifié | F11: Une amélioration est identifiée si les indicateurs de performance ne correspondent pas à l'ambition du projet (par exemple, plus de 2 secondes pour afficher une page web). | G11: Modéré | I11: =ifs( E11="🤔 À évaluer",0, E11="⌛️ Évaluation en cours",0.5, E11="✅ Point fort confirmé",0, E11="💡 Potentiel d'amélioration identifié",1, E11="🚫 Non applicable",0, TRUE, 0) -> 1 | J11: =ifs( G11="Modéré", 1, G11="Significatif", 1.5, G11="Déterminant", 2, TRUE,0) -> 1 | K11: =I11*J11 -> 1
B12: 45782 | C12: Les cas d'utilisation les plus critiques (parcours utilisateurs les plus fréquents) sont-ils optimisés ? | D12: Les parcours utilisateur les plus fréquents sont essentiels pour l'ensemble des ressources utilisées par l'application. L'application d'optimisations sur ces chemins de code devrait donner de bons résultats. | E12: ✅ Point fort confirmé | F12: Une amélioration est identifiée si aucune étude n'a été menée pour améliorer les performances/l'efficacité des chemins de code les plus utilisés. | G12: Significatif | I12: =ifs( E12="🤔 À évaluer",0, E12="⌛️ Évaluation en cours",0.5, E12="✅ Point fort confirmé",0, E12="💡 Potentiel d'amélioration identifié",1, E12="🚫 Non applicable",0, TRUE, 0) -> 0 | J12: =ifs( G12="Modéré", 1, G12="Significatif", 1.5, G12="Déterminant", 2, TRUE,0) -> 1.5 | K12: =I12*J12 -> 0
B13: 45813 | C13: La pile technique (Java, JS, Python, PHP, etc.)est-elle pas à jour ? | D13: La mise à jour des outils (tels que la machine virtuelle Java) permet d'améliorer àmoindre coût les performances et l'efficacité. | E13: ⌛️ Évaluation en cours | F13: Une amélioration est identifiée si la base technique du projet n'est pas à jour au moins jusqu'à la dernière version LTS. | G13: Significatif | I13: =ifs( E13="🤔 À évaluer",0, E13="⌛️ Évaluation en cours",0.5, E13="✅ Point fort confirmé",0, E13="💡 Potentiel d'amélioration identifié",1, E13="🚫 Non applicable",0, TRUE, 0) -> 0.5 | J13: =ifs( G13="Modéré", 1, G13="Significatif", 1.5, G13="Déterminant", 2, TRUE,0) -> 1.5 | K13: =I13*J13 -> 0.75
B14: 45843 | C14: Les composants peuvent-ils être réglés pour améliorer l'efficacité ? | D14: Les composants d'optimisation (tels que la machine virtuelle Java) permettent d'améliorer les performances et l'efficacité. | E14: 🤔 À évaluer | F14: Une amélioration est identifiée si aucune étude n'a été menée pour vérifier si l'efficacité des composants déployés pourrait être améliorée en modifiant leur configuration. | G14: Modéré | I14: =ifs( E14="🤔 À évaluer",0, E14="⌛️ Évaluation en cours",0.5, E14="✅ Point fort confirmé",0, E14="💡 Potentiel d'amélioration identifié",1, E14="🚫 Non applicable",0, TRUE, 0) -> 0 | J14: =ifs( G14="Modéré", 1, G14="Significatif", 1.5, G14="Déterminant", 2, TRUE,0) -> 1 | K14: =I14*J14 -> 0
B15: 45874 | C15: Les dépendances du projet sont-elles à jour ? | D15: La mise à jour des dépendances du projet (comme le Spring Framework en Java) peut permettre d'améliorer les performances et l'efficacité. | E15: 🚫 Non applicable | F15: Une amélioration est identifiée si les principales dépendances du projet ne sont pas à jour par rapport à la dernière version stable. | G15: Déterminant | I15: =ifs( E15="🤔 À évaluer",0, E15="⌛️ Évaluation en cours",0.5, E15="✅ Point fort confirmé",0, E15="💡 Potentiel d'amélioration identifié",1, E15="🚫 Non applicable",0, TRUE, 0) -> 0 | J15: =ifs( G15="Modéré", 1, G15="Significatif", 1.5, G15="Déterminant", 2, TRUE,0) -> 2 | K15: =I15*J15 -> 0
B16: 45905 | C16: Des problèmes de compatibilité ont-ils été identifiés pour les appareils ciblés ? | D16: Le service doit être compatible avec tous les appareils dont disposent les utilisateurs afin d'éviter que ces appareils ne deviennent obsolètes. | F16: Une amélioration est identifiée si l'équipe a détecté des problèmes de compatibilité. | G16: Déterminant | I16: =ifs( E16="🤔 À évaluer",0, E16="⌛️ Évaluation en cours",0.5, E16="✅ Point fort confirmé",0, E16="💡 Potentiel d'amélioration identifié",1, E16="🚫 Non applicable",0, TRUE, 0) -> 0 | J16: =ifs( G16="Modéré", 1, G16="Significatif", 1.5, G16="Déterminant", 2, TRUE,0) -> 2 | K16: =I16*J16 -> 0
A18: Licence CC-BY-SA

Sheet 🛠6-Facilité de changement
C2: 🛠 Facilité de changement | F2: Potentiel d'optimisation | I2: =SUM(I8:I18) -> 0 | J2: =SUM(J8:J18) -> 15.5 | K2: =SUM(K8:K18) -> 0
C3: Identifiez les meilleures opportunités d'optimisation. | F3: =IF(I2= 0, 0,K2 / J2) -> 0
F4: Un score plus élevé reflète un potentiel d'optimisation plus important. | I4: Score | J4: Poids numerique | K4: Weighted Score
B7: ID # | C7: CRITÈRE | D7: EXPLICATION SUPPLÉMENTAIRE | E7: ✏️ ÉVALUATION | F7: MÉTHODES D'ÉVALUATION | G7: NIVEAU D'IMPACT
B8: 6.1 | C8: Existe-t-il un dispositif d'observabilité efficace pour le produit ? | D8: Sans un minimum de connaissances sur le comportement du produit en cours d'exécution, il est difficile d'identifier les optimisations possibles. L'absence de surveillance implique un faible potentiel d'optimisation. | F8: Le critère est validé si des outils d'observabilité sont en place. | G8: Déterminant | I8: =ifs( E8="🤔 À évaluer",0, E8="⌛️ Évaluation en cours",0.5, E8="🟢 Facile à changer",1, E8="🟡 Effort modéré",0.5, E8="🔴 Difficile à changer",0.25, E8="🚫 Non applicable",0, TRUE, 0) -> 0 | J8: =ifs( G8="Modéré", 1, G8="Significatif", 1.5, G8="Déterminant", 2, TRUE,0) -> 2 | K8: =I8*J8 -> 0
B9: 6.2 | C9: Existe-t-il des revues de code et/ou une programmation en binôme ( pair programming)? | D9: Les revues de code et la programmation en binôme garantissent un niveau minimum de connaissances communes sur la base de code et une qualité minimale. | F9: Le critère est validé si des revues de code et de la programmation en binôme sont effectuées sur la majeure partie du code du projet. | G9: Significatif | I9: =ifs( E9="🤔 À évaluer",0, E9="⌛️ Évaluation en cours",0.5, E9="🟢 Facile à changer",1, E9="🟡 Effort modéré",0.5, E9="🔴 Difficile à changer",0.25, E9="🚫 Non applicable",0, TRUE, 0) -> 0 | J9: =ifs( G9="Modéré", 1, G9="Significatif", 1.5, G9="Déterminant", 2, TRUE,0) -> 1.5 | K9: =I9*J9 -> 0
B10: 6.3 | C10: Existe-t-il un processus CI/CD efficace ? | D10: La présence d'un CI/CD est un bon indicateur de la facilité avec laquelle il sera possible de travailler sur l'application en toute confiance. | F10: Le critère est validé si les projets sont régulièrement construits et testés automatiquement via un outil CI/CD. | G10: Significatif | I10: =ifs( E10="🤔 À évaluer",0, E10="⌛️ Évaluation en cours",0.5, E10="🟢 Facile à changer",1, E10="🟡 Effort modéré",0.5, E10="🔴 Difficile à changer",0.25, E10="🚫 Non applicable",0, TRUE, 0) -> 0 | J10: =ifs( G10="Modéré", 1, G10="Significatif", 1.5, G10="Déterminant", 2, TRUE,0) -> 1.5 | K10: =I10*J10 -> 0
B11: 6.4 | C11: Existe-t-il des tests de non-régression (tests unitaires, tests d'intégration, tests de bout en bout) ? | D11: La présence de tests de non-régression permet aux programmeurs de modifier le logiciel tout en étant assurés de l'absence de problèmes induits par leur travail. | F11: Le critère est validé si le projet dispose d'un ensemble complet de tests automatisés couvrant les parties les plus importantes du code source. | G11: Déterminant | I11: =ifs( E11="🤔 À évaluer",0, E11="⌛️ Évaluation en cours",0.5, E11="🟢 Facile à changer",1, E11="🟡 Effort modéré",0.5, E11="🔴 Difficile à changer",0.25, E11="🚫 Non applicable",0, TRUE, 0) -> 0 | J11: =ifs( G11="Modéré", 1, G11="Significatif", 1.5, G11="Déterminant", 2, TRUE,0) -> 2 | K11: =I11*J11 -> 0
B12: 6.5 | C12: Y a-t-il un fort découplage entre le domaine métier et l'intégration technique ? | D12: Les pratiques de découplage telles que l'injection de dépendances ou l'architecture hexagonale/propre/en oignon permettent des changements techniques plus efficaces et ambitieux. C'est le « D » (inversion des dépendances) des 5 principes fondamentaux. | F12: Le critère est validé s'il est possible de modifier les aspects techniques du produit sans modifier le code fonctionnel. | G12: Significatif | I12: =ifs( E12="🤔 À évaluer",0, E12="⌛️ Évaluation en cours",0.5, E12="🟢 Facile à changer",1, E12="🟡 Effort modéré",0.5, E12="🔴 Difficile à changer",0.25, E12="🚫 Non applicable",0, TRUE, 0) -> 0 | J12: =ifs( G12="Modéré", 1, G12="Significatif", 1.5, G12="Déterminant", 2, TRUE,0) -> 1.5 | K12: =I12*J12 -> 0
B13: 6.6 | C13: Existe-t-il des indicateurs permettant de suivre la qualité des logiciels ? | D13: Comme la couverture de code, la complexité cyclomatique, le nombre de problèmes, le nombre de problèmes de livraison, le nombre de retours en arrière, le délai de modification, la fréquence de déploiement, le pourcentage d'échecs de modification, le temps de récupération après un déploiement échoué. | F13: Le critère est validé si des mesures de qualité logicielle sont en place. | G13: Déterminant | I13: =ifs( E13="🤔 À évaluer",0, E13="⌛️ Évaluation en cours",0.5, E13="🟢 Facile à changer",1, E13="🟡 Effort modéré",0.5, E13="🔴 Difficile à changer",0.25, E13="🚫 Non applicable",0, TRUE, 0) -> 0 | J13: =ifs( G13="Modéré", 1, G13="Significatif", 1.5, G13="Déterminant", 2, TRUE,0) -> 2 | K13: =I13*J13 -> 0
B14: 6.7 | C14: Existe-t-il une documentation complète ? | D14: La présence d'une documentation pertinente permet des changements plus ambitieux. | F14: Le critère est validé si le projet dispose d'une documentation claire et utilisable. | G14: Significatif | I14: =ifs( E14="🤔 À évaluer",0, E14="⌛️ Évaluation en cours",0.5, E14="🟢 Facile à changer",1, E14="🟡 Effort modéré",0.5, E14="🔴 Difficile à changer",0.25, E14="🚫 Non applicable",0, TRUE, 0) -> 0 | J14: =ifs( G14="Modéré", 1, G14="Significatif", 1.5, G14="Déterminant", 2, TRUE,0) -> 1.5 | K14: =I14*J14 -> 0
B15: 6.8 | C15: Y a-t-il du code dupliqué dans l'application ? | D15: Le code dupliqué peut être supprimé afin de simplifier la maintenance des produits. | F15: Le critère est validé s'il n'y a pas de code dupliqué injustifié dans le projet. | G15: Modéré | I15: =ifs( E15="🤔 À évaluer",0, E15="⌛️ Évaluation en cours",0.5, E15="🟢 Facile à changer",1, E15="🟡 Effort modéré",0.5, E15="🔴 Difficile à changer",0.25, E15="🚫 Non applicable",0, TRUE, 0) -> 0 | J15: =ifs( G15="Modéré", 1, G15="Significatif", 1.5, G15="Déterminant", 2, TRUE,0) -> 1 | K15: =I15*J15 -> 0
B16: 6.9 | C16: L'équipe dispose-t-elle d'une autonomie suffisante pour déployer les outils dont elle a besoin pour observer, mesurer ou optimiser le système ? | D16: La facilité de changement augmente lorsque les équipes peuvent compter sur les outils dont elles ont besoin pour surveiller les performances, mesurer l'impact ou analyser les comportements. Cette autonomie peut provenir de la possibilité d'installer des outils personnalisés ou de s'appuyer sur des outils intégrés complets fournis par la plateforme. Ce qui importe, ce n'est pas l'endroit où l'infrastructure est hébergée, mais la capacité de l'équipe à l'utiliser efficacement pour soutenir l'optimisation. | F16: Le critère est validé si l'équipe peut utiliser ou déployer les outils dont elle a besoin pour observer, mesurer et optimiser le système. | G16: Modéré | I16: =ifs( E16="🤔 À évaluer",0, E16="⌛️ Évaluation en cours",0.5, E16="🟢 Facile à changer",1, E16="🟡 Effort modéré",0.5, E16="🔴 Difficile à changer",0.25, E16="🚫 Non applicable",0, TRUE, 0) -> 0 | J16: =ifs( G16="Modéré", 1, G16="Significatif", 1.5, G16="Déterminant", 2, TRUE,0) -> 1 | K16: =I16*J16 -> 0
B17: 6.10 | C17: Les composants principaux sont-ils soumis à des contraintes de haute disponibilité ? | D17: Les exigences de haute disponibilité peuvent réduire la capacité de l'équipe à modifier, migrer ou optimiser les composants. Les services qui doivent maintenir une disponibilité stricte laissent moins de possibilités pour les fenêtres de maintenance, les changements architecturaux ou l'optimisation des ressources. Comprendre ces contraintes aide à évaluer la facilité avec laquelle le système peut évoluer vers un impact environnemental moindre. | F17: Le critère est validé si les contraintes de disponibilité du système permettent encore à l'équipe de modifier ou d'optimiser les composants sans difficulté majeure. | G17: Significatif | I17: =ifs( E17="🤔 À évaluer",0, E17="⌛️ Évaluation en cours",0.5, E17="🟢 Facile à changer",1, E17="🟡 Effort modéré",0.5, E17="🔴 Difficile à changer",0.25, E17="🚫 Non applicable",0, TRUE, 0) -> 0 | J17: =ifs( G17="Modéré", 1, G17="Significatif", 1.5, G17="Déterminant", 2, TRUE,0) -> 1.5 | K17: =I17*J17 -> 0

Sheet 🕸️ 7-Synthèse
B2: 🕸️ Synthèse | J2: Score global d'optimisation potentielle
B3: Aperçu du potentiel d'optimisation pour tous les critères | J3: =IF(SUM(C7:C11)=0, 0,(('🛖 1-Produit'!K2+'🗺️ 2-Architecture'!K2+'🏢 3-Infrastructure'!K2+'💾 4-Stockage et données'!K2+ '👨‍💻5-Algo & Code'!K2) / ('🛖 1-Produit'!J2+'🗺️ 2-Architecture'!J2+'🏢 3-Infrastructure'!J2+'💾 4-Stockage et données'!J2+ '👨‍💻5-Algo & Code'!J2))) -> 0.36821705
J4: Un score plus élevé reflète un potentiel d'optimisation plus important.
B6: CATÉGORIES | C6: SCORE
B7: ='🛖 1-Produit'!C2 -> 🛖 Produit | C7: ='🛖 1-Produit'!F3 -> 0.27659574
B8: ='🗺️ 2-Architecture'!C2 -> 🗺️ Architecture | C8: ='🗺️ 2-Architecture'!F3 -> 0.625
B9: ='🏢 3-Infrastructure'!C2 -> 🏢 Infrastructure | C9: ='🏢 3-Infrastructure'!F3 -> 0.25
B10: ='💾 4-Stockage et données'!C2 -> 💾 Storage & Data | C10: ='💾 4-Stockage et données'!F3 -> 0.5625
B11: ='👨‍💻5-Algo & Code'!C2 -> 👨‍💻 Algo & Code | C11: ='👨‍💻5-Algo & Code'!F3 -> 0.36538462
B12: ='🛠6-Facilité de changement'!C2 -> 🛠 Facilité de changement | C12: ='🛠6-Facilité de changement'!F3 -> 0
B24: `
A33: Licence CC-BY-SA
A36: Number of criteria of "🏦-0-Quick Diagnosis" | B36: =COUNTA('🏦 0-Diagnostic rapide'!C9:C27) -> 16
A37: Number of criteria of " Potential optimization global score" | B37: =COUNTA('🛖 1-Produit'!C8:C57)+COUNTA(#REF!)+COUNTA('🏢 -3- Infrastructure (💬)'!C4:C50)+COUNTA('💾-4-Storage&Data (💬)'!C4:C52)+COUNTA('👨‍💻-5-Algo & Code (✅)'!C4:C50) -> 20
A38: Number of criteria of "🛠-6- Ease of change" | B38: =COUNTA('🛠6-Facilité de changement'!C8:C20) -> 10
A39: Number of overall criteria | B39: =SUM(B36:B38) -> 46
